[
  {
    "id": 14,
    "ticket_group_id": 17,
    "ticket_group_title": "it",
    "title": "خرابی پرینتر",
    "description": "",
    "created_at": "5/8/2024 07:36:22",
    "assigned_at": "5/8/2024 07:37:18",
    "ticket_time": "",
    "status": 7,
    "author_name": "امیر کریمی",
    "supporter_name": "محسن محمدی ک",
    "ldap_display_name": null,
    "agreement_name": "پایا",
    "closed_at": null,
    "ticket_full_time": null
  },
  {
    "id": 13,
    "ticket_group_id": 17,
    "ticket_group_title": "it",
    "title": "jsj",
    "description": "kljdbcvjkadbdhkvb",
    "created_at": "1/8/2024 10:52:40",
    "assigned_at": "1/8/2024 10:57:34",
    "ticket_time": "",
    "status": 8,
    "author_name": "امیر کریمی",
    "supporter_name": "محسن محمدی ک",
    "ldap_display_name": null,
    "agreement_name": "پایا",
    "closed_at": "1/8/2024 10:58:30",
    "ticket_full_time": "00:00:56"
  },
  {
    "id": 12,
    "ticket_group_id": 17,
    "ticket_group_title": "it",
    "title": "مشکل تست",
    "description": "مشکل تست",
    "created_at": "23/7/2024 11:23:47",
    "assigned_at": "23/7/2024 11:24:43",
    "ticket_time": "",
    "status": 8,
    "author_name": "امیر کریمی",
    "supporter_name": "محسن محمدی ک",
    "ldap_display_name": null,
    "agreement_name": "پایا",
    "closed_at": "24/7/2024 11:30:18",
    "ticket_full_time": "24:05:35"
  },
  {
    "id": 11,
    "ticket_group_id": 16,
    "ticket_group_title": "حسابرس",
    "title": "مشکل عدم تطبیق حساب",
    "description": "مشکل عدم تطبیق حساب",
    "created_at": "22/7/2024 19:02:04",
    "assigned_at": "22/7/2024 19:23:14",
    "ticket_time": "",
    "status": 8,
    "author_name": "امیر کریمی",
    "supporter_name": "حمیدرضا کاظمی",
    "ldap_display_name": null,
    "agreement_name": "پایا",
    "closed_at": "22/7/2024 19:38:58",
    "ticket_full_time": "00:15:44"
  },
  {
    "id": 10,
    "ticket_group_id": 17,
    "ticket_group_title": "it",
    "title": "مشکل پرینتر ",
    "description": "پرینتر مشکل عدم چاپ دارد",
    "created_at": "22/7/2024 19:00:25",
    "assigned_at": "22/7/2024 19:11:10",
    "ticket_time": "",
    "status": 8,
    "author_name": "امیر کریمی",
    "supporter_name": "محسن محمدی ک",
    "ldap_display_name": null,
    "agreement_name": "پایا",
    "closed_at": "22/7/2024 19:40:20",
    "ticket_full_time": "00:29:10"
  },
  {
    "id": 9,
    "ticket_group_id": 17,
    "ticket_group_title": "it",
    "title": "مشکل پرینتر ",
    "description": "پرینتر مشکل عدم چاپ دارد",
    "created_at": "22/7/2024 19:00:21",
    "assigned_at": null,
    "ticket_time": "",
    "status": 8,
    "author_name": "امیر کریمی",
    "supporter_name": "محسن محمدی",
    "ldap_display_name": null,
    "agreement_name": "پایا",
    "closed_at": "22/7/2024 19:19:57",
    "ticket_full_time": null
  },
  {
    "id": 8,
    "ticket_group_id": 17,
    "ticket_group_title": "it",
    "title": "مشکل پرینتر ",
    "description": "پرینتر مشکل عدم چاپ دارد",
    "created_at": "22/7/2024 19:00:21",
    "assigned_at": null,
    "ticket_time": "",
    "status": 8,
    "author_name": "امیر کریمی",
    "supporter_name": "محسن محمدی",
    "ldap_display_name": null,
    "agreement_name": "پایا",
    "closed_at": "22/7/2024 19:09:59",
    "ticket_full_time": null
  }
]